PyCybex-1.2.2.dist-info/METADATA
PyCybex-1.2.2.dist-info/RECORD
PyCybex-1.2.2.dist-info/WHEEL
PyCybex-1.2.2.dist-info/top_level.txt
cybex/__init__.py
cybex/account.py
cybex/address.py
cybex/asset.py
cybex/balance.py
cybex/custom.py
cybex/cybex.py
cybex/cybex_objects.py
cybex/cybex_operations.py
cybex/cybex_types.py
cybex/dice.py
cybex/exceptions.py
cybex/exchange.py
cybex/gateway.py
cybex/intercept_bitshares.py
cybex/market.py
cybex/nonfungible.py
cybex/types.py
cybex/wallet.py
