Metadata-Version: 2.1
Name: PyCybex
Version: 1.2.2
Summary: Use this lib to visit public data on cybex decentralized exchange like account, marketing, asset and balance.Also, it can be used to manage a wallet for user and send transactions to cybex chain
Home-page: https://github.com/CybexDEX/cybex-node-doc
Author: yoyo.zhou
Author-email: yoyo.zhou@cybex.io
License: UNKNOWN
Platform: UNKNOWN
Classifier: Programming Language :: Python :: 3
Classifier: License :: OSI Approved :: MIT License
Classifier: Operating System :: OS Independent
Requires-Dist: bitshares (==0.1.13)
Requires-Dist: graphenelib (==0.6.1)
Requires-Dist: requests (>=2.19.0)
Requires-Dist: coincurve (==11.0.0)
Requires-Dist: websockets (==6.0)
